README.rst
setup.py
vroom/__init__.py
vroom/area_codes.yml
vroom/plates_parser.py
vroom/regex_patterns.yml
vroom.egg-info/PKG-INFO
vroom.egg-info/SOURCES.txt
vroom.egg-info/dependency_links.txt
vroom.egg-info/requires.txt
vroom.egg-info/top_level.txt