Metadata-Version: 1.0
Name: vroom
Version: 1.0.2
Summary: License Plate Parser
Home-page: https://github.com/magdanowak/vroom
Author: Magdalena Nowak
Author-email: magdanowak0804@gmail.com
License: MIT
Platform: UNKNOWN
